{
    "appid": "1100760",
    "type": "Tool",
    "name": "Football Manager 2020 Editor",
    "schinese_name": "",
    "isfreeapp": "0",
    "change_number": "26972615",
    "update_time": "2025-01-13 21:31:22",
    "depot": {
        "1100761": {
            "config": {
                "oslist": "windows",
                "osarch": "64"
            },
            "manifests": {
                "public": {
                    "gid": "8526681449704103278",
                    "size": "47412760",
                    "download": "14601104"
                },
                "public-beta": {
                    "gid": "8526681449704103278",
                    "size": "47412760",
                    "download": "14601104"
                }
            },
            "decryptionkey": "6c5f81c7df32e789cfbad96901649bba64debb7f53a96a7c93f11792ba63fdd5"
        },
        "1100762": {
            "config": {
                "oslist": "macos"
            },
            "manifests": {
                "public": {
                    "gid": "6130497693611376241",
                    "size": "41100153",
                    "download": "12885568"
                },
                "public-beta": {
                    "gid": "6130497693611376241",
                    "size": "41100153",
                    "download": "12885568"
                }
            },
            "decryptionkey": ""
        },
        "baselanguages": "english,german,french,italian,koreana,spanish,schinese,tchinese,russian,portuguese,polish,danish,dutch,norwegian,swedish,turkish,greek",
        "branches": {
            "public": {
                "buildid": "4738889",
                "timeupdated": "1583431087"
            },
            "public-beta": {
                "buildid": "4738889",
                "timeupdated": "1583431075"
            }
        },
        "privatebranches": "1"
    }
}