{
    "appid": 1114220,
    "name": "Gedonia",
    "type": "Game",
    "schinese_name": "",
    "isfreeapp": 0,
    "update_time": "2025-05-28 01:06:54",
    "change_number": 29217911,
    "depot": {
        "1114221": {
            "config": {
                "oslist": "windows",
                "language": ""
            },
            "manifests": {
                "public": {
                    "gid": "5994977893344718600",
                    "size": "9765909128",
                    "download": "3439859632"
                }
            },
            "decryptionkey": "23b3bfba02672961ab0943997b88291097953e6006eed793d3452dbe3c212db9"
        },
        "baselanguages": "english,russian",
        "workshopdepot": "1114220",
        "branches": {
            "public": {
                "buildid": "16727998",
                "timeupdated": "1734074040"
            }
        },
        "workshopdepotdecryptionkey": "cb6661de4088401eecc5f58edaadd5a53db28b4e7f943778ad22ab4cebdcc558"
    }
}