{
    "appid": 2427050,
    "name": "Munch",
    "type": "Game",
    "schinese_name": "",
    "isfreeapp": 0,
    "update_time": "2025-05-30 03:23:24",
    "change_number": 29268315,
    "depot": {
        "2427051": {
            "config": {
                "oslist": "windows"
            },
            "manifests": {
                "public": {
                    "gid": "4606815881855059895",
                    "size": "3665731091",
                    "download": "1696086064"
                }
            },
            "decryptionkey": "37fc263e5a9773e6494df5b4490ad4fa822390ad3a3c551a1da7fb3d18481b3a"
        },
        "2427052": {
            "config": {
                "oslist": "macos"
            },
            "manifests": {
                "public": {
                    "gid": "6962351074095630758",
                    "size": "3698077932",
                    "download": "1704436880"
                }
            }
        },
        "branches": {
            "public": {
                "buildid": "18117236",
                "timeupdated": "1744739143"
            }
        },
        "privatebranches": "1"
    }
}