{
    "appid": 2443360,
    "name": "Zortch",
    "type": "Game",
    "schinese_name": "",
    "isfreeapp": 0,
    "update_time": "2025-06-02 23:10:29",
    "change_number": 29321927,
    "depot": {
        "2443361": {
            "manifests": {
                "public": {
                    "gid": "6016832095267293337",
                    "size": "368385159",
                    "download": "306077840"
                },
                "beta": {
                    "gid": "3673364722076420839",
                    "size": "368317912",
                    "download": "306230224"
                }
            },
            "decryptionkey": "1d09f6d8665f0877db0f069f2017db184b924fc3e3a3925fef35dc3102906a21"
        },
        "workshopdepot": "2443360",
        "branches": {
            "public": {
                "buildid": "17658549",
                "timeupdated": "1741593974"
            },
            "beta": {
                "buildid": "14653069",
                "description": "New feature testing",
                "timeupdated": "1717890450"
            }
        },
        "workshopdepotdecryptionkey": "9207a3182c4e310edf14a2f58c69610be71a11451fecdd01156fb4cffb22ec60"
    }
}