{
    "appid": "2541890",
    "type": "Game",
    "name": "Abnormality",
    "schinese_name": "",
    "isfreeapp": "0",
    "change_number": "28760573",
    "update_time": "2025-05-01 08:19:38",
    "depot": {
        "228989": {
            "config": {
                "oslist": "windows"
            },
            "depotfromapp": "228980",
            "sharedinstall": "1"
        },
        "228990": {
            "config": {
                "oslist": "windows"
            },
            "depotfromapp": "228980",
            "sharedinstall": "1"
        },
        "229003": {
            "config": {
                "oslist": "windows"
            },
            "depotfromapp": "228980",
            "sharedinstall": "1"
        },
        "2541891": {
            "manifests": {
                "public": {
                    "gid": "3504597470064872216",
                    "size": "9580632174",
                    "download": "9338641904"
                }
            },
            "decryptionkey": "0eabedd8c6ec1d99ce99c56c005c647ee33a6bd06bdfd4712474ec5d05e66c06"
        },
        "branches": {
            "public": {
                "buildid": "16378670",
                "timeupdated": "1731416680"
            }
        },
        "privatebranches": "1"
    }
}