{
    "appid": "2578120",
    "type": "Demo",
    "name": "Tenebris Somnia Demo",
    "schinese_name": "",
    "isfreeapp": "0",
    "change_number": "25759136",
    "update_time": "2024-10-17 10:46:31",
    "depot": {
        "228989": {
            "config": {
                "oslist": "windows"
            },
            "depotfromapp": "228980",
            "sharedinstall": "1"
        },
        "228990": {
            "config": {
                "oslist": "windows"
            },
            "depotfromapp": "228980",
            "sharedinstall": "1"
        },
        "2578121": {
            "manifests": {
                "public": {
                    "gid": "2881202834026851212",
                    "size": "482991615",
                    "download": "391950240"
                }
            },
            "decryptionkey": "25cb22a2c1dbcb507ef5fd330dfec7558058c0daeb1263ca3e2c8bec85480333"
        },
        "branches": {
            "public": {
                "buildid": "16023044",
                "timeupdated": "1728924674"
            }
        },
        "privatebranches": "1"
    }
}