{
    "appid": 3093880,
    "name": "Cauldron's Rift",
    "type": "Game",
    "schinese_name": "",
    "isfreeapp": 0,
    "update_time": "2025-06-11 09:19:09",
    "change_number": 29497466,
    "depot": {
        "3093881": {
            "manifests": {
                "public": {
                    "gid": "7381783518027746991",
                    "size": "156603814",
                    "download": "46322400"
                }
            },
            "decryptionkey": "c73d7b267246b5d6ae62e59bcd7c9709894eaad573bb9bd385e7e2d1b7eb90c4"
        },
        "branches": {
            "public": {
                "buildid": "18505905",
                "timeupdated": "1749604741"
            }
        },
        "privatebranches": "1"
    }
}