{
    "appid": "46420",
    "type": "Game",
    "name": "Chrome",
    "schinese_name": "",
    "isfreeapp": "0",
    "change_number": "19661327",
    "update_time": "2024-05-25 08:21:18",
    "depot": {
        "46421": {
            "systemdefined": "1",
            "manifests": {
                "public": {
                    "gid": "2659886543139862547",
                    "size": "1862804159",
                    "download": "0"
                }
            },
            "decryptionkey": "54c46cce28b45e868447c614ff28b2b73ebd74a4f300e3691418451d02c05c34"
        },
        "overridescddb": "1",
        "branches": {
            "public": {
                "buildid": "21414"
            }
        }
    }
}