{
    "appid": "466980",
    "type": "Game",
    "name": "Can't Drive This",
    "schinese_name": "",
    "isfreeapp": "0",
    "change_number": "26752724",
    "update_time": "2024-12-22 19:21:55",
    "depot": {
        "baselanguages": "english",
        "466982": {
            "config": {
                "oslist": "windows"
            },
            "manifests": {
                "public": {
                    "gid": "6838630628716321010",
                    "size": "1491965025",
                    "download": "274010880"
                },
                "legacy": {
                    "gid": "2085625670359295239",
                    "size": "445985870",
                    "download": "115355360"
                }
            },
            "decryptionkey": "529a5a0574bafb0bdbff6ec58be7d31ab46ec4677c51644ca91a21d0d59bfb57"
        },
        "466983": {
            "config": {
                "oslist": "macos"
            },
            "manifests": {
                "public": {
                    "gid": "2037061186814077773",
                    "size": "1567375382",
                    "download": "295734592"
                },
                "legacy": {
                    "gid": "3151222341129517403",
                    "size": "499862348",
                    "download": "130231872"
                }
            },
            "decryptionkey": ""
        },
        "466984": {
            "config": {
                "oslist": "linux"
            },
            "manifests": {
                "public": {
                    "gid": "6366480907020838152",
                    "size": "1616518810",
                    "download": "315774032"
                },
                "legacy": {
                    "gid": "1426610703075009391",
                    "size": "503339207",
                    "download": "133153936"
                }
            },
            "decryptionkey": ""
        },
        "branches": {
            "public": {
                "buildid": "6402082",
                "timeupdated": "1616108403"
            },
            "legacy": {
                "buildid": "2095926",
                "description": "The old version Can't Drive This.",
                "timeupdated": "1585728331"
            }
        },
        "privatebranches": "1"
    }
}