{
    "appid": "470590",
    "type": "Game",
    "name": "moto RKD dash",
    "schinese_name": "",
    "isfreeapp": "0",
    "change_number": "28973828",
    "update_time": "2025-05-14 13:17:44",
    "depot": {
        "baselanguages": "english",
        "470591": {
            "config": {
                "oslist": "windows"
            },
            "manifests": {
                "public": {
                    "gid": "8206774035395268596",
                    "size": "540060275",
                    "download": "143009168"
                }
            },
            "decryptionkey": "5bcdd771bb53a7d06591c211fddb971c57dcfd28a69de05a40474ec89d410fdd"
        },
        "470592": {
            "config": {
                "oslist": "macos",
                "osarch": "64"
            },
            "manifests": {
                "public": {
                    "gid": "4009638855702244818",
                    "size": "535979517",
                    "download": "145977152"
                }
            },
            "decryptionkey": ""
        },
        "470593": {
            "config": {
                "oslist": "linux"
            },
            "manifests": {
                "public": {
                    "gid": "6877721080468358907",
                    "size": "552538124",
                    "download": "150351696"
                }
            },
            "decryptionkey": ""
        },
        "branches": {
            "public": {
                "buildid": "3140991",
                "timeupdated": "1548516372"
            }
        },
        "privatebranches": "1"
    }
}