{
    "appid": "493900",
    "type": "Game",
    "name": "Dungeons 3",
    "schinese_name": "地下城3",
    "isfreeapp": "0",
    "change_number": "28974020",
    "update_time": "2025-05-14 13:37:52",
    "depot": {
        "baselanguages": "",
        "hasdepotsindlc": "1",
        "228986": {
            "config": {
                "oslist": "windows"
            },
            "depotfromapp": "228980",
            "sharedinstall": "1"
        },
        "493901": {
            "config": {
                "language": ""
            },
            "manifests": {
                "public": {
                    "gid": "2775552542639382064",
                    "size": "1035495712",
                    "download": "945229024"
                }
            },
            "decryptionkey": "b588bce72c60112a04f6ebd87405bc49de589daaf560e03c65bf22e975864523"
        },
        "493902": {
            "config": {
                "oslist": "windows",
                "language": ""
            },
            "manifests": {
                "public": {
                    "gid": "939440225510644531",
                    "size": "5389969743",
                    "download": "1640780400"
                }
            },
            "decryptionkey": "e4a67c793fe21ae3b2f4dc11e734714b4b1c17ce1cea5b63d90ecf86b3aabcc5"
        },
        "493903": {
            "config": {
                "oslist": "macos",
                "language": ""
            },
            "manifests": {
                "public": {
                    "gid": "7685672873360296073",
                    "size": "5230521725",
                    "download": "1607252800"
                }
            },
            "decryptionkey": "685ad973d6d850eddf4bb66da43254a67db226f9d4116f594f67b51a1cc57137"
        },
        "493904": {
            "config": {
                "oslist": "linux",
                "language": ""
            },
            "manifests": {
                "public": {
                    "gid": "3190433396352764059",
                    "size": "5232700563",
                    "download": "1612896256"
                }
            },
            "decryptionkey": "1590354074cd1274e018c819eba3c162c43d7547f3cfd64217b3419c00692e56"
        },
        "493905": {
            "config": {
                "language": ""
            },
            "manifests": {
                "public": {
                    "gid": "69194741727597605",
                    "size": "57971463",
                    "download": "57512336"
                }
            },
            "decryptionkey": ""
        },
        "630099": {
            "config": {
                "language": "english"
            },
            "manifests": {
                "public": {
                    "gid": "5166559558394442309",
                    "size": "346705851",
                    "download": "345888176"
                }
            },
            "decryptionkey": "594a14477e71e418bf93dc7c39dd329cf63a7c4e28286067a88bd0828976c61e"
        },
        "630098": {
            "config": {
                "language": "german"
            },
            "manifests": {
                "public": {
                    "gid": "8257181552979181607",
                    "size": "450270271",
                    "download": "449312944"
                }
            },
            "decryptionkey": "9b50caf7a54df0c27d41d2bcfcf4dbba7816c7b3cac8ea855019aff2c22d4fe2"
        },
        "630097": {
            "config": {
                "language": "french"
            },
            "manifests": {
                "public": {
                    "gid": "3925560497192100164",
                    "size": "366880939",
                    "download": "366076464"
                }
            },
            "decryptionkey": "fd9dd68f4b8b115b184627029878e5c898935d8319b772ebab62c5bd7caacce7"
        },
        "630095": {
            "config": {
                "language": "spanish"
            },
            "manifests": {
                "public": {
                    "gid": "3829487861480892519",
                    "size": "416737115",
                    "download": "416156288"
                }
            },
            "decryptionkey": "6cd3d47805720c3034bfefaeebe59aaa44ef0d0d2818368cdd49e59cfddcbb0b"
        },
        "630096": {
            "config": {
                "language": "italian"
            },
            "manifests": {
                "public": {
                    "gid": "8122392579335576184",
                    "size": "390985799",
                    "download": "390492304"
                }
            },
            "decryptionkey": "dbd83f691d72653680c0bfbc0f94f3b5655e2f9c79d7410c89bb87c73e8bf6c4"
        },
        "630094": {
            "config": {
                "language": "russian"
            },
            "manifests": {
                "public": {
                    "gid": "7748160672160024775",
                    "size": "386380623",
                    "download": "384943888"
                }
            },
            "decryptionkey": "4af24660da65691368ec8b428b270e267fe5b8548a1138716f78f9206a3324c4"
        },
        "630093": {
            "config": {
                "language": "schinese"
            },
            "manifests": {
                "public": {
                    "gid": "1609205731082324659",
                    "size": "346557539",
                    "download": "345859952"
                }
            },
            "decryptionkey": "e3a57f2ff220b1ce504dbbb7206525a776fd1e34060c67259bf27a7277a29d54"
        },
        "711173": {
            "config": {
                "language": "koreana"
            },
            "manifests": {
                "public": {
                    "gid": "1697567128491993564",
                    "size": "346866031",
                    "download": "345906976"
                }
            },
            "decryptionkey": "7e2078926b4c70c85f4615cefcd806f2a74789d9907a013aca9776b14386ea4e"
        },
        "493906": {
            "config": {
                "language": "czech"
            },
            "manifests": {
                "public": {
                    "gid": "5469672841208890142",
                    "size": "346701819",
                    "download": "345901152"
                }
            },
            "decryptionkey": "c0ed3502d424327e4c3510431dafda13fbf26493f03676533c01fea48125807e"
        },
        "493907": {
            "config": {
                "language": "japanese"
            },
            "manifests": {
                "public": {
                    "gid": "8044520254740145778",
                    "size": "346905943",
                    "download": "345904736"
                }
            },
            "decryptionkey": "13fb5b5e70b52c76283542a5122d943aeb411f2afedde29accdabf0c2afb6f4e"
        },
        "711174": {
            "dlcappid": "711170",
            "config": {
                "oslist": "windows",
                "language": ""
            },
            "manifests": {
                "public": {
                    "gid": "2685240387369957167",
                    "size": "1034474",
                    "download": "222640"
                }
            },
            "decryptionkey": "22a5f8608559c477a0b5adca30feae399fa7903a4042960dd9a91f7f6d70db7e"
        },
        "711175": {
            "dlcappid": "711170",
            "config": {
                "oslist": "macos",
                "language": ""
            },
            "manifests": {
                "public": {
                    "gid": "8431729652115591299",
                    "size": "1034474",
                    "download": "222368"
                }
            },
            "decryptionkey": "046c7f1950f46da5484483ddffd91b911d69f10096c943707312267363a7acaf"
        },
        "711176": {
            "dlcappid": "711170",
            "config": {
                "oslist": "linux",
                "language": ""
            },
            "manifests": {
                "public": {
                    "gid": "3249584465115270379",
                    "size": "1034474",
                    "download": "221840"
                }
            },
            "decryptionkey": "c5ea8a60603ed14d09f9e5dd748a5369d96786cc2455ff3a9cf73dfdfddb6688"
        },
        "711177": {
            "dlcappid": "711171",
            "config": {
                "oslist": "windows",
                "language": ""
            },
            "manifests": {
                "public": {
                    "gid": "1483424363995958111",
                    "size": "1320462",
                    "download": "328816"
                }
            },
            "decryptionkey": "50bf75bc66bd2219c761f92d1eba7302fc5e80712bebb3d7d39356f97bc6dfa3"
        },
        "711178": {
            "dlcappid": "711171",
            "config": {
                "oslist": "macos",
                "language": ""
            },
            "manifests": {
                "public": {
                    "gid": "9087154153454105935",
                    "size": "1320462",
                    "download": "329088"
                }
            },
            "decryptionkey": "90add3fd1ac441503804fed24aebf9089d8fb4354f910cbfd54902ab4b43d5c3"
        },
        "711179": {
            "dlcappid": "711171",
            "config": {
                "oslist": "linux",
                "language": ""
            },
            "manifests": {
                "public": {
                    "gid": "7098362530139807282",
                    "size": "1320462",
                    "download": "329088"
                }
            },
            "decryptionkey": "f64fcbe8d3064c30e483e2debf438f5f93d0a779ddbf5e35f1a4de5e458b97e2"
        },
        "711682": {
            "dlcappid": "630090",
            "config": {
                "oslist": "windows",
                "language": ""
            },
            "manifests": {
                "public": {
                    "gid": "5112760202501054068",
                    "size": "14",
                    "download": "64"
                }
            },
            "decryptionkey": "f1f058ed034ca08438426851ed363ff00c63d29b13ee32eaa47ad4917cbadb2e"
        },
        "711683": {
            "dlcappid": "630090",
            "config": {
                "oslist": "macos",
                "language": ""
            },
            "manifests": {
                "public": {
                    "gid": "5508118338173642702",
                    "size": "14",
                    "download": "64"
                }
            },
            "decryptionkey": ""
        },
        "711684": {
            "dlcappid": "630090",
            "config": {
                "oslist": "linux",
                "language": ""
            },
            "manifests": {
                "public": {
                    "gid": "763263295188253299",
                    "size": "14",
                    "download": "64"
                }
            },
            "decryptionkey": ""
        },
        "711685": {
            "dlcappid": "630091",
            "config": {
                "oslist": "windows",
                "language": ""
            },
            "manifests": {
                "public": {
                    "gid": "8028467847671402178",
                    "size": "14",
                    "download": "64"
                }
            },
            "decryptionkey": "32ef2e052ca5d99e5c04c056692d961b91039b6b71f8c4ae1d1497fc9e3ae41c"
        },
        "711686": {
            "dlcappid": "630091",
            "config": {
                "oslist": "macos",
                "language": ""
            },
            "manifests": {
                "public": {
                    "gid": "418080747894322703",
                    "size": "14",
                    "download": "64"
                }
            },
            "decryptionkey": "32683f1b1526e2244d93ee2bbd58139504adca2ecd49f7d7474be96eac559cf2"
        },
        "711687": {
            "dlcappid": "630091",
            "config": {
                "oslist": "linux",
                "language": ""
            },
            "manifests": {
                "public": {
                    "gid": "7422613405638393561",
                    "size": "14",
                    "download": "64"
                }
            },
            "decryptionkey": "919e659868b8890024fe2f4225fba3e69be8065d65430ecbadcde177eeafb7ed"
        },
        "711688": {
            "dlcappid": "630092",
            "config": {
                "oslist": "windows",
                "language": ""
            },
            "manifests": {
                "public": {
                    "gid": "6421062162663487459",
                    "size": "15",
                    "download": "64"
                }
            },
            "decryptionkey": ""
        },
        "711689": {
            "dlcappid": "630092",
            "config": {
                "oslist": "macos",
                "language": ""
            },
            "manifests": {
                "public": {
                    "gid": "2299439018262204205",
                    "size": "15",
                    "download": "64"
                }
            },
            "decryptionkey": ""
        },
        "724160": {
            "dlcappid": "630092",
            "config": {
                "oslist": "linux",
                "language": ""
            },
            "manifests": {
                "public": {
                    "gid": "3486832356997282679",
                    "size": "15",
                    "download": "64"
                }
            },
            "decryptionkey": ""
        },
        "724161": {
            "dlcappid": "711172",
            "config": {
                "oslist": "windows",
                "language": ""
            },
            "manifests": {
                "public": {
                    "gid": "3678833174644234453",
                    "size": "2138336",
                    "download": "248304"
                }
            },
            "decryptionkey": "8b1f7d54da2e54bc9ccc242aa321f0c3968f071a80dbaa27aedd830e0d19ac29"
        },
        "724162": {
            "dlcappid": "711172",
            "config": {
                "oslist": "macos",
                "language": ""
            },
            "manifests": {
                "public": {
                    "gid": "7187363388675523114",
                    "size": "2138336",
                    "download": "248304"
                }
            },
            "decryptionkey": "7ca004b54718ec37fe9cf7bcf7774efe4b6fb41036e7b36a77bced38441b27cc"
        },
        "724163": {
            "dlcappid": "711172",
            "config": {
                "oslist": "linux",
                "language": ""
            },
            "manifests": {
                "public": {
                    "gid": "5351587958090427787",
                    "size": "2138336",
                    "download": "248304"
                }
            },
            "decryptionkey": "f3b4b930b29007395b44e449df841f0689f5d716f9715d106cd0dac916524ffe"
        },
        "724164": {
            "dlcappid": "711680",
            "config": {
                "oslist": "windows",
                "language": ""
            },
            "manifests": {
                "public": {
                    "gid": "9145586336952054638",
                    "size": "1566179",
                    "download": "184816"
                }
            },
            "decryptionkey": "e43144b0c95195e223a6c043619d3405a005750d4acb8e1e18320b81aaf2b3ac"
        },
        "724165": {
            "dlcappid": "711680",
            "config": {
                "oslist": "macos",
                "language": ""
            },
            "manifests": {
                "public": {
                    "gid": "4519720030200692681",
                    "size": "1566179",
                    "download": "184816"
                }
            },
            "decryptionkey": "5086056646010ef2f226f78976c34a23de0609d1ffc7e7ba51d50da8d5a1da74"
        },
        "724166": {
            "dlcappid": "711680",
            "config": {
                "oslist": "linux",
                "language": ""
            },
            "manifests": {
                "public": {
                    "gid": "2341825319447214587",
                    "size": "1566179",
                    "download": "184816"
                }
            },
            "decryptionkey": "24510fae8a7c4dd5b26b856948fe6cec9a1fe6024fc1523e268a3acfcae737c5"
        },
        "724167": {
            "dlcappid": "711681",
            "config": {
                "oslist": "windows",
                "language": ""
            },
            "manifests": {
                "public": {
                    "gid": "4601001480219346549",
                    "size": "2229569",
                    "download": "248544"
                }
            },
            "decryptionkey": "5831131d7ff987ce31f082d6a99e3117e0346ebec3e9722c7f1a56823aa15321"
        },
        "724168": {
            "dlcappid": "711681",
            "config": {
                "oslist": "macos",
                "language": ""
            },
            "manifests": {
                "public": {
                    "gid": "1440741728372950411",
                    "size": "2229569",
                    "download": "248544"
                }
            },
            "decryptionkey": "4e92d8b222036fd1e90ef767e4e699917d31fd6e0e33df1a26173c81296bec3a"
        },
        "724169": {
            "dlcappid": "711681",
            "config": {
                "oslist": "linux",
                "language": ""
            },
            "manifests": {
                "public": {
                    "gid": "2409509269956414170",
                    "size": "2229569",
                    "download": "248544"
                }
            },
            "decryptionkey": "8ff6b0ea997556099cd8e498ed78d97a802e61ae5c48cd057fc6c595cc6118c8"
        },
        "824611": {
            "dlcappid": "824610",
            "config": {
                "oslist": "windows",
                "language": ""
            },
            "manifests": {
                "public": {
                    "gid": "7815349823550083216",
                    "size": "5599067",
                    "download": "624736"
                }
            },
            "decryptionkey": "3fef2c8bc1b377abf06f56c6a0fff15e987231b5e3f258e27ebfc5488fe2d0bb"
        },
        "824612": {
            "dlcappid": "824610",
            "config": {
                "oslist": "macos",
                "language": ""
            },
            "manifests": {
                "public": {
                    "gid": "6840427282119688656",
                    "size": "5599067",
                    "download": "624736"
                }
            },
            "decryptionkey": "f61af4be955e8acee3fc0711ab1aa7c876c1df73ee173feaedaefec7636f231a"
        },
        "824613": {
            "dlcappid": "824610",
            "config": {
                "oslist": "linux",
                "language": ""
            },
            "manifests": {
                "public": {
                    "gid": "5960947599195789187",
                    "size": "5599067",
                    "download": "624736"
                }
            },
            "decryptionkey": "b8ffe1caae8d34b2f340cdad21f3f81a9149d58514fad82e0732b69ab2d90ea6"
        },
        "824614": {
            "dlcappid": "975330",
            "config": {
                "oslist": "windows",
                "language": ""
            },
            "manifests": {
                "public": {
                    "gid": "1455656009896730477",
                    "size": "965901",
                    "download": "263408"
                }
            },
            "decryptionkey": "835353b019e417c2af8285794b520bf02f945982166c33d5648ac8f774a88657"
        },
        "824615": {
            "dlcappid": "975330",
            "config": {
                "oslist": "macos",
                "language": ""
            },
            "manifests": {
                "public": {
                    "gid": "2367396990468038496",
                    "size": "965901",
                    "download": "263408"
                }
            },
            "decryptionkey": "c3c3d27e8731323190466bf89edfef8779e24c9b723e0bfb3f5f7644196f85ff"
        },
        "824616": {
            "dlcappid": "975330",
            "config": {
                "oslist": "linux",
                "language": ""
            },
            "manifests": {
                "public": {
                    "gid": "8702714712945404538",
                    "size": "965901",
                    "download": "263408"
                }
            },
            "decryptionkey": "10575ca8c6a4facde1e41d89a5250e625e580efa5441510aa5b5bd47e55a45b6"
        },
        "824617": {
            "dlcappid": "975360",
            "config": {
                "oslist": "windows",
                "language": ""
            },
            "manifests": {
                "public": {
                    "gid": "7713150565719865021",
                    "size": "2071733",
                    "download": "224832"
                }
            },
            "decryptionkey": "d4061b6cfadf546130d108956ff5cf2ccc94f6ade8c2041f86e322e2f7882125"
        },
        "824618": {
            "dlcappid": "975360",
            "config": {
                "oslist": "macos",
                "language": ""
            },
            "manifests": {
                "public": {
                    "gid": "7377545132797474729",
                    "size": "2071733",
                    "download": "224832"
                }
            },
            "decryptionkey": "6ade19916c989cbbf839439a02729a9ba8e230b73cc475b0cc4ee338dca26d32"
        },
        "824619": {
            "dlcappid": "975360",
            "config": {
                "oslist": "linux",
                "language": ""
            },
            "manifests": {
                "public": {
                    "gid": "445341766642944383",
                    "size": "2071733",
                    "download": "224832"
                }
            },
            "decryptionkey": "be1817a94d85b0365f16ba4b0ec04ca58ce68ba0f85624c3a2694ea64da135ae"
        },
        "975331": {
            "dlcappid": "1023950",
            "config": {
                "oslist": "windows",
                "language": ""
            },
            "manifests": {
                "public": {
                    "gid": "4718988624969077080",
                    "size": "722445",
                    "download": "195632"
                }
            },
            "decryptionkey": "fc34b6f32f62f1f83ec20488fcebfb2417fca076eb2c76fc5febc5e73121c36c"
        },
        "975332": {
            "dlcappid": "1023950",
            "config": {
                "oslist": "macos",
                "language": ""
            },
            "manifests": {
                "public": {
                    "gid": "7965240410468835850",
                    "size": "722445",
                    "download": "195632"
                }
            },
            "decryptionkey": "450ec50165e0ba539d405a75663ffef57570368da33d4b40e3d48cb32cca5f7c"
        },
        "975333": {
            "dlcappid": "1023950",
            "config": {
                "oslist": "linux",
                "language": ""
            },
            "manifests": {
                "public": {
                    "gid": "6960493500828815674",
                    "size": "722445",
                    "download": "196160"
                }
            },
            "decryptionkey": "b143798b35998d7a40a22799944ec3020bc29e9f5ace96e65a8d9d1700394803"
        },
        "975334": {
            "dlcappid": "1049940",
            "config": {
                "oslist": "windows",
                "language": ""
            },
            "manifests": {
                "public": {
                    "gid": "727480190278895948",
                    "size": "2261668",
                    "download": "234096"
                }
            },
            "decryptionkey": "2e8277941c1885397f291f444672b029ddbaa75fbbf382899c370b736b3ca171"
        },
        "975335": {
            "dlcappid": "1049940",
            "config": {
                "oslist": "macos",
                "language": ""
            },
            "manifests": {
                "public": {
                    "gid": "457652418997633435",
                    "size": "2261668",
                    "download": "234096"
                }
            },
            "decryptionkey": ""
        },
        "975336": {
            "dlcappid": "1049940",
            "config": {
                "oslist": "linux",
                "language": ""
            },
            "manifests": {
                "public": {
                    "gid": "1773249835665003367",
                    "size": "2261668",
                    "download": "234096"
                }
            },
            "decryptionkey": ""
        },
        "975337": {
            "dlcappid": "1198940",
            "config": {
                "oslist": "windows",
                "language": ""
            },
            "manifests": {
                "public": {
                    "gid": "2072019601914885356",
                    "size": "1774420",
                    "download": "193488"
                }
            },
            "decryptionkey": "5e0e1f98f18aa3b7dbe04db5aab010fde4862a6fa10fb123cf7b91f69c2866cf"
        },
        "975338": {
            "dlcappid": "1198940",
            "config": {
                "oslist": "macos",
                "language": ""
            },
            "manifests": {
                "public": {
                    "gid": "1931166270802767363",
                    "size": "1774420",
                    "download": "193488"
                }
            },
            "decryptionkey": ""
        },
        "975339": {
            "dlcappid": "1198940",
            "config": {
                "oslist": "linux",
                "language": ""
            },
            "manifests": {
                "public": {
                    "gid": "1512009281723732771",
                    "size": "1774420",
                    "download": "193488"
                }
            },
            "decryptionkey": ""
        },
        "branches": {
            "public": {
                "buildid": "7363028",
                "timeupdated": "1631793431"
            }
        },
        "privatebranches": "1"
    }
}