{
    "appid": "570550",
    "type": "Game",
    "name": "Fearful Symmetry",
    "schinese_name": "",
    "isfreeapp": "0",
    "change_number": "18903802",
    "update_time": "2024-06-22 11:07:40",
    "depot": {
        "570551": {
            "config": {
                "oslist": "windows"
            },
            "manifests": {
                "public": {
                    "gid": "7737890648064156342",
                    "size": "64101330",
                    "download": "41215888"
                }
            },
            "decryptionkey": "057d5419ffd18e24aeb085dea6eb26f7076f060a812125f42394c49460892608"
        },
        "branches": {
            "public": {
                "buildid": "1748827",
                "timeupdated": "1491910665"
            }
        }
    }
}