{
    "appid": "601940",
    "type": "Game",
    "name": "Fancy Fishing VR",
    "schinese_name": "",
    "isfreeapp": "0",
    "change_number": "23591175",
    "update_time": "2024-05-26 17:40:30",
    "depot": {
        "baselanguages": "english,schinese",
        "601941": {
            "config": {
                "oslist": "windows"
            },
            "manifests": {
                "public": {
                    "gid": "7705016443778580119",
                    "size": "519150798",
                    "download": "194342496"
                }
            },
            "decryptionkey": "b70a41668b71c58395cd0fba71965c027c5a42865f64483dceb15936e5bbd467"
        },
        "branches": {
            "public": {
                "buildid": "1666058",
                "timeupdated": "1488507855"
            }
        },
        "privatebranches": "1"
    }
}