{
    "appid": 645830,
    "name": "Son Korsan",
    "type": "Game",
    "schinese_name": "",
    "isfreeapp": 1,
    "update_time": "2025-05-26 01:16:40",
    "change_number": 29178968,
    "depot": {
        "645831": {
            "config": {
                "oslist": "windows"
            },
            "manifests": {
                "public": {
                    "gid": "2541808979850924836",
                    "size": "650608345",
                    "download": "83914240"
                }
            },
            "decryptionkey": "447fcc8ae2284b46a96a2b734af83b3dd7358b04b81e0bf0c7820c809f7efe69"
        },
        "branches": {
            "public": {
                "buildid": "17074475",
                "timeupdated": "1737446336"
            }
        }
    }
}