{
    "appid": "690670",
    "type": "Game",
    "name": "Klondike Solitaire Kings",
    "schinese_name": "",
    "isfreeapp": "0",
    "change_number": "28589667",
    "update_time": "2025-04-22 05:22:59",
    "depot": {
        "690671": {
            "config": {
                "oslist": "windows"
            },
            "manifests": {
                "public": {
                    "gid": "4082138286258387694",
                    "size": "78310901",
                    "download": "31440576"
                }
            },
            "decryptionkey": "c94622f15122559a19895cb4b1420f746746593095d939f78e23217ec28646e8"
        },
        "748280": {
            "config": {
                "oslist": "windows"
            },
            "dlcappid": "748280",
            "manifests": {
                "public": {
                    "gid": "8397766388593423313",
                    "size": "72330292",
                    "download": "20523120"
                }
            },
            "decryptionkey": ""
        },
        "749280": {
            "config": {
                "oslist": "windows"
            },
            "dlcappid": "749280",
            "manifests": {
                "public": {
                    "gid": "9196746558199152073",
                    "size": "72328564",
                    "download": "21063936"
                }
            },
            "decryptionkey": ""
        },
        "749620": {
            "config": {
                "oslist": "windows"
            },
            "manifests": {
                "public": {
                    "gid": "2947333483397627349",
                    "size": "72330490",
                    "download": "19856096"
                }
            },
            "dlcappid": "749620",
            "decryptionkey": ""
        },
        "branches": {
            "public": {
                "buildid": "2259238",
                "timeupdated": "1509903393"
            }
        }
    }
}