{
    "appid": "867480",
    "type": "Game",
    "name": "Daddy",
    "schinese_name": "",
    "isfreeapp": "0",
    "change_number": "28979783",
    "update_time": "2025-05-14 22:47:31",
    "depot": {
        "baselanguages": "english",
        "867489": {
            "config": {
                "oslist": "windows"
            },
            "manifests": {
                "public": {
                    "gid": "4958855648375636946",
                    "size": "287017340",
                    "download": "82041936"
                }
            },
            "decryptionkey": "0ad156a90bea462e1131736084246c33187248d034f1780790cf920460e0315d"
        },
        "branches": {
            "public": {
                "buildid": "2811235",
                "timeupdated": "1527470573"
            }
        }
    }
}