{
    "appid": 997360,
    "name": "Super Animal Royale Soundtrack",
    "type": "Music",
    "schinese_name": "",
    "isfreeapp": 0,
    "update_time": "2025-06-09 13:22:49",
    "change_number": 29455365,
    "depot": {
        "997360": {
            "config": {
                "language": ""
            },
            "manifests": {
                "public": {
                    "gid": "4196476903340776609",
                    "size": "393802027",
                    "download": "327874096"
                }
            },
            "decryptionkey": "5ef5c0cb3038dd981c6d6368ffdba4ab5fe51799a3df7bfdc00c9d5cf8d80443"
        },
        "997361": {
            "config": {
                "highqualityaudio": "1",
                "language": ""
            },
            "manifests": {
                "public": {
                    "gid": "1438071033987059103",
                    "size": "960699503",
                    "download": "970877984"
                }
            },
            "decryptionkey": "a1561cdef84e62b0edac30422b2a2b1367e31a95bd47dceaa6a9e9d325dbadca"
        },
        "branches": {
            "public": {
                "buildid": "16127981",
                "timeupdated": "1729546095"
            }
        }
    }
}